LICENSE
MANIFEST.in
README.rst
setup.py
bee_django_exam/__init__.py
bee_django_exam/admin.py
bee_django_exam/apps.py
bee_django_exam/decorators.py
bee_django_exam/exports.py
bee_django_exam/forms.py
bee_django_exam/models.py
bee_django_exam/signals.py
bee_django_exam/tests.py
bee_django_exam/urls.py
bee_django_exam/utils.py
bee_django_exam/views.py
bee_django_exam.egg-info/PKG-INFO
bee_django_exam.egg-info/SOURCES.txt
bee_django_exam.egg-info/dependency_links.txt
bee_django_exam.egg-info/requires.txt
bee_django_exam.egg-info/top_level.txt
bee_django_exam/migrations/.DS_Store
bee_django_exam/migrations/0001_initial.py
bee_django_exam/migrations/0001_initial.pyc
bee_django_exam/migrations/0002_auto_20180112_1812.py
bee_django_exam/migrations/0002_auto_20180112_1812.pyc
bee_django_exam/migrations/0003_auto_20180112_1821.py
bee_django_exam/migrations/0003_auto_20180112_1821.pyc
bee_django_exam/migrations/0004_auto_20180114_1415.py
bee_django_exam/migrations/0004_auto_20180114_1415.pyc
bee_django_exam/migrations/0005_auto_20180114_1417.py
bee_django_exam/migrations/0005_auto_20180114_1417.pyc
bee_django_exam/migrations/0006_auto_20180114_1418.py
bee_django_exam/migrations/0006_auto_20180114_1418.pyc
bee_django_exam/migrations/0007_userexamrecord_passed_date.py
bee_django_exam/migrations/0007_userexamrecord_passed_date.pyc
bee_django_exam/migrations/0008_auto_20180114_1558.py
bee_django_exam/migrations/0008_auto_20180114_1558.pyc
bee_django_exam/migrations/0009_auto_20180118_1520.py
bee_django_exam/migrations/0009_auto_20180118_1520.pyc
bee_django_exam/migrations/0010_auto_20180118_1534.py
bee_django_exam/migrations/0010_auto_20180118_1534.pyc
bee_django_exam/migrations/0011_auto_20180118_1719.py
bee_django_exam/migrations/0011_auto_20180118_1719.pyc
bee_django_exam/migrations/0012_remove_grade_cert_image.py
bee_django_exam/migrations/0012_remove_grade_cert_image.pyc
bee_django_exam/migrations/0013_grade_cert_image.py
bee_django_exam/migrations/0013_grade_cert_image.pyc
bee_django_exam/migrations/0014_auto_20180119_1522.py
bee_django_exam/migrations/0014_auto_20180119_1522.pyc
bee_django_exam/migrations/0015_auto_20180119_1523.py
